badwords_r.py
badwords_r-1.0.0.dist-info/WHEEL
badwords_r-1.0.0.dist-info/METADATA
badwords_r-1.0.0.dist-info/RECORD
